[
	{
		"constant": false,
		"inputs": [
			{
				"internalType": "uint256",
				"name": "pollId",
				"type": "uint256"
			},
			{
				"internalType": "address",
				"name": "newVoter",
				"type": "address"
			}
		],
		"name": "addVoter",
		"outputs": [],
		"payable": false,
		"stateMutability": "nonpayable",
		"type": "function"
	},
	{
		"constant": false,
		"inputs": [
			{
				"internalType": "string",
				"name": "_name",
				"type": "string"
			},
			{
				"internalType": "string",
				"name": "_uri",
				"type": "string"
			},
			{
				"internalType": "uint256",
				"name": "pollDeadlineInHours",
				"type": "uint256"
			}
		],
		"name": "createPoll",
		"outputs": [
			{
				"internalType": "uint256",
				"name": "",
				"type": "uint256"
			}
		],
		"payable": false,
		"stateMutability": "nonpayable",
		"type": "function"
	},
	{
		"inputs": [],
		"payable": false,
		"stateMutability": "nonpayable",
		"type": "constructor"
	},
	{
		"constant": false,
		"inputs": [
			{
				"internalType": "uint256",
				"name": "pollId",
				"type": "uint256"
			},
			{
				"internalType": "bool",
				"name": "support",
				"type": "bool"
			}
		],
		"name": "vote",
		"outputs": [],
		"payable": false,
		"stateMutability": "nonpayable",
		"type": "function"
	},
	{
		"constant": true,
		"inputs": [],
		"name": "chairperson",
		"outputs": [
			{
				"internalType": "address payable",
				"name": "",
				"type": "address"
			}
		],
		"payable": false,
		"stateMutability": "view",
		"type": "function"
	},
	{
		"constant": true,
		"inputs": [
			{
				"internalType": "uint256",
				"name": "pollId",
				"type": "uint256"
			}
		],
		"name": "hasMajority",
		"outputs": [
			{
				"internalType": "bool",
				"name": "",
				"type": "bool"
			}
		],
		"payable": false,
		"stateMutability": "view",
		"type": "function"
	},
	{
		"constant": true,
		"inputs": [],
		"name": "NumberOfPolls",
		"outputs": [
			{
				"internalType": "uint256",
				"name": "",
				"type": "uint256"
			}
		],
		"payable": false,
		"stateMutability": "view",
		"type": "function"
	},
	{
		"constant": true,
		"inputs": [
			{
				"internalType": "uint256",
				"name": "",
				"type": "uint256"
			},
			{
				"internalType": "address",
				"name": "",
				"type": "address"
			}
		],
		"name": "pollCommittee",
		"outputs": [
			{
				"internalType": "bool",
				"name": "",
				"type": "bool"
			}
		],
		"payable": false,
		"stateMutability": "view",
		"type": "function"
	},
	{
		"constant": true,
		"inputs": [
			{
				"internalType": "uint256",
				"name": "",
				"type": "uint256"
			}
		],
		"name": "polls",
		"outputs": [
			{
				"internalType": "string",
				"name": "name",
				"type": "string"
			},
			{
				"internalType": "string",
				"name": "uri",
				"type": "string"
			},
			{
				"internalType": "uint256",
				"name": "voteCount",
				"type": "uint256"
			},
			{
				"internalType": "uint256",
				"name": "voteSupport",
				"type": "uint256"
			},
			{
				"internalType": "uint256",
				"name": "pollId",
				"type": "uint256"
			},
			{
				"internalType": "uint256",
				"name": "pollDeadlineInHours",
				"type": "uint256"
			}
		],
		"payable": false,
		"stateMutability": "view",
		"type": "function"
	},
	{
		"constant": true,
		"inputs": [
			{
				"internalType": "uint256",
				"name": "",
				"type": "uint256"
			},
			{
				"internalType": "address",
				"name": "",
				"type": "address"
			}
		],
		"name": "pollVoters",
		"outputs": [
			{
				"internalType": "bool",
				"name": "",
				"type": "bool"
			}
		],
		"payable": false,
		"stateMutability": "view",
		"type": "function"
	}
]